{
  "muscleGroups": [
    { "id": 1, "nameKey": "muscle.chest", "image": "chest.png" },
    { "id": 2, "nameKey": "muscle.back", "image": "back.png" },
    { "id": 3, "nameKey": "muscle.shoulders", "image": "shoulders.png" },
    { "id": 4, "nameKey": "muscle.biceps", "image": "biceps.png" },
    { "id": 5, "nameKey": "muscle.triceps", "image": "triceps.png" },
    { "id": 6, "nameKey": "muscle.legs", "image": "legs.png" },
    { "id": 7, "nameKey": "muscle.abs", "image": "abs.png" },
    { "id": 8, "nameKey": "muscle.other", "image": "other.png" }
  ],
  "exerciseType": [
    {"id": 1, "nameKey": "type.weight_training"},
    {"id": 2, "nameKey": "type.bodyweight"},
    {"id": 3, "nameKey": "type.bench"},
    {"id": 4, "nameKey": "type.cardio"},
    {"id": 5, "nameKey": "type.flexibility"},
    {"id": 6, "nameKey": "type.functional"},
    {"id": 7, "nameKey": "type.powerlifting"},
    {"id": 8, "nameKey": "type.olympic_lifting"},
    {"id": 9, "nameKey": "type.isometric"},
    {"id": 10, "nameKey": "type.plyometric"},
    {"id": 11, "nameKey": "type.resistance_band"},
    {"id": 12, "nameKey": "type.kettlebell"},
    {"id": 13, "nameKey": "type.cable_machine"},
    {"id": 14, "nameKey": "type.machine_based"},
    {"id": 15, "nameKey": "type.free_weights"},
    {"id": 16, "nameKey": "type.core_training"},
    {"id": 17, "nameKey": "type.high_intensity"},
    {"id": 18, "nameKey": "type.low_impact"},
    {"id": 19, "nameKey": "type.stability"},
    {"id": 20, "nameKey": "type.mobility"}
  ],
  "exercises": [
    {
      "id": 1,
      "nameKey": "exercise.bench_press.name",
      "descriptionKey": "exercise.bench_press.description",
      "image": "bench_press.gif",
      "exerciseTypeKey": "1",
      "muscleGroupId": 1,
      "createdByUser": false,
      "unilateral": false
    },
    {
      "id": 2,
      "nameKey": "exercise.pull_up.name",
      "descriptionKey": "exercise.pull_up.description",
      "image": "pull_up.gif",
      "exerciseTypeKey": "2",
      "muscleGroupId": 2,
      "createdByUser": false,
      "unilateral": false
    },
    {
      "id": 3,
      "nameKey": "exercise.barbell_curl.name",
      "descriptionKey": "exercise.barbell_curl.description",
      "image": "barbell_curl.gif",
      "exerciseTypeKey": "1",
      "muscleGroupId": 4,
      "createdByUser": false,
      "unilateral": false
    },
    {
      "id": 4,
      "nameKey": "exercise.preacher_curl.name",
      "descriptionKey": "exercise.preacher_curl.description",
      "image": "preacher_curl.gif",
      "exerciseTypeKey": "1",
      "muscleGroupId": 4,
      "createdByUser": false,
      "unilateral": false
    },
    {
      "id": 5,
      "nameKey": "exercise.cable_biceps_hammer.name",
      "descriptionKey": "exercise.cable_biceps_hammer.description",
      "image": "cable_biceps_hammer.gif",
      "exerciseTypeKey": "13",
      "muscleGroupId": 4,
      "createdByUser": false,
      "unilateral": false
    },
    {
      "id": 6,
      "nameKey": "exercise.cable_biceps_neutral.name",
      "descriptionKey": "exercise.cable_biceps_neutral.description",
      "image": "cable_biceps_neutral.gif",
      "exerciseTypeKey": "13",
      "muscleGroupId": 4,
      "createdByUser": false,
      "unilateral": false
    },
    {
      "id": 7,
      "nameKey": "exercise.concentration_curl_hammer.name",
      "descriptionKey": "exercise.concentration_curl_hammer.description",
      "image": "concentration_curl_hammer.gif",
      "exerciseTypeKey": "1",
      "muscleGroupId": 4,
      "createdByUser": false,
      "unilateral": false
    },
    {
      "id": 8,
      "nameKey": "exercise.concentration_curl_neutral.name",
      "descriptionKey": "exercise.concentration_curl_neutral.description",
      "image": "concentration_curl_neutral.gif",
      "exerciseTypeKey": "1",
      "muscleGroupId": 4,
      "createdByUser": false,
      "unilateral": false
    },
    {
      "id": 9,
      "nameKey": "exercise.hammer_curl.name",
      "descriptionKey": "exercise.hammer_curl.description",
      "image": "hammer_curl.gif",
      "exerciseTypeKey": "1",
      "muscleGroupId": 4,
      "createdByUser": false,
      "unilateral": true
    },
    {
      "id": 10,
      "nameKey": "exercise.dumbbell_curl.name",
      "descriptionKey": "exercise.dumbbell_curl.description",
      "image": "dumbbell_curl.gif",
      "exerciseTypeKey": "1",
      "muscleGroupId": 4,
      "createdByUser": false,
      "unilateral": true
    },
    {
      "id": 11,
      "nameKey": "exercise.incline_dumbbell_curl.name",
      "descriptionKey": "exercise.incline_dumbbell_curl.description",
      "image": "incline_dumbbell_curl.gif",
      "exerciseTypeKey": "1",
      "muscleGroupId": 4,
      "createdByUser": false,
      "unilateral": true
    },
    {
      "id": 12,
      "nameKey": "exercise.incline_hammer_curl.name",
      "descriptionKey": "exercise.incline_hammer_curl.description",
      "image": "incline_hammer_curl.gif",
      "exerciseTypeKey": "1",
      "muscleGroupId": 4,
      "createdByUser": false,
      "unilateral": true
    },
    {
      "id": 13,
      "nameKey": "exercise.incline_bench_press.name",
      "descriptionKey": "exercise.incline_bench_press.description",
      "image": "incline_bench_press.gif",
      "exerciseTypeKey": "1",
      "muscleGroupId": 1,
      "createdByUser": false,
      "unilateral": false
    },
    {
      "id": 14,
      "nameKey": "exercise.dumbbell_bench_press.name",
      "descriptionKey": "exercise.dumbbell_bench_press.description",
      "image": "dumbbell_bench_press.gif",
      "exerciseTypeKey": "15",
      "muscleGroupId": 1,
      "createdByUser": false,
      "unilateral": false
    },
    {
      "id": 15,
      "nameKey": "exercise.incline_dumbbell_press.name",
      "descriptionKey": "exercise.incline_dumbbell_press.description",
      "image": "incline_dumbbell_press.gif",
      "exerciseTypeKey": "15",
      "muscleGroupId": 1,
      "createdByUser": false,
      "unilateral": false
    },
    {
      "id": 16,
      "nameKey": "exercise.pec_fly.name",
      "descriptionKey": "exercise.pec_fly.description",
      "image": "pec_fly.gif",
      "exerciseTypeKey": "15",
      "muscleGroupId": 1,
      "createdByUser": false,
      "unilateral": false
    },
    {
      "id": 17,
      "nameKey": "exercise.cable_crossover.name",
      "descriptionKey": "exercise.cable_crossover.description",
      "image": "cable_crossover.gif",
      "exerciseTypeKey": "13",
      "muscleGroupId": 1,
      "createdByUser": false,
      "unilateral": false
    },
    {
      "id": 18,
      "nameKey": "exercise.dips_chest.name",
      "descriptionKey": "exercise.dips_chest.description",
      "image": "dips_chest.gif",
      "exerciseTypeKey": "2",
      "muscleGroupId": 1,
      "createdByUser": false,
      "unilateral": false
    },
    {
      "id": 19,
      "nameKey": "exercise.push_up.name",
      "descriptionKey": "exercise.push_up.description",
      "image": "push_up.gif",
      "exerciseTypeKey": "2",
      "muscleGroupId": 1,
      "createdByUser": false,
      "unilateral": false
    },
    {
      "id": 20,
      "nameKey": "exercise.machine_chest_press.name",
      "descriptionKey": "exercise.machine_chest_press.description",
      "image": "machine_chest_press.gif",
      "exerciseTypeKey": "14",
      "muscleGroupId": 1,
      "createdByUser": false,
      "unilateral": false
    },

    {
      "id": 21,
      "nameKey": "exercise.skull_crusher.name",
      "descriptionKey": "exercise.skull_crusher.description",
      "image": "skull_crusher.gif",
      "exerciseTypeKey": "1",
      "muscleGroupId": 5,
      "createdByUser": false,
      "unilateral": false
    },
    {
      "id": 23,
      "nameKey": "exercise.dips_triceps.name",
      "descriptionKey": "exercise.dips_triceps.description",
      "image": "dips_triceps.gif",
      "exerciseTypeKey": "2",
      "muscleGroupId": 5,
      "createdByUser": false,
      "unilateral": false
    },
    {
      "id": 24,
      "nameKey": "exercise.machine_dips.name",
      "descriptionKey": "exercise.machine_dips.description",
      "image": "machine_dips.gif",
      "exerciseTypeKey": "14",
      "muscleGroupId": 5,
      "createdByUser": false,
      "unilateral": false
    },
    {
      "id": 25,
      "nameKey": "exercise.dumbbell_triceps_extension.name",
      "descriptionKey": "exercise.dumbbell_triceps_extension.description",
      "image": "dumbbell_triceps_extension.gif",
      "exerciseTypeKey": "15",
      "muscleGroupId": 5,
      "createdByUser": false,
      "unilateral": true
    },
    {
      "id": 26,
      "nameKey": "exercise.cable_triceps_extension.name",
      "descriptionKey": "exercise.cable_triceps_extension.description",
      "image": "cable_triceps_extension.gif",
      "exerciseTypeKey": "13",
      "muscleGroupId": 5,
      "createdByUser": false,
      "unilateral": false
    },
    {
      "id": 27,
      "nameKey": "exercise.triceps_kickback.name",
      "descriptionKey": "exercise.triceps_kickback.description",
      "image": "triceps_kickback.gif",
      "exerciseTypeKey": "15",
      "muscleGroupId": 5,
      "createdByUser": false,
      "unilateral": true
    },
    {
      "id": 28,
      "nameKey": "exercise.overhead_triceps_extension.name",
      "descriptionKey": "exercise.overhead_triceps_extension.description",
      "image": "overhead_triceps_extension.gif",
      "exerciseTypeKey": "15",
      "muscleGroupId": 5,
      "createdByUser": false,
      "unilateral": true
    },
    {
      "id": 29,
      "nameKey": "exercise.lying_triceps_extension.name",
      "descriptionKey": "exercise.lying_triceps_extension.description",
      "image": "lying_triceps_extension.gif",
      "exerciseTypeKey": "15",
      "muscleGroupId": 5,
      "createdByUser": false,
      "unilateral": false
    },

    {
      "id": 30,
      "nameKey": "exercise.arnold_press.name",
      "descriptionKey": "exercise.arnold_press.description",
      "image": "arnold_press.gif",
      "exerciseTypeKey": "15",
      "muscleGroupId": 3,
      "createdByUser": false,
      "unilateral": false
    },
    {
      "id": 31,
      "nameKey": "exercise.military_press.name",
      "descriptionKey": "exercise.military_press.description",
      "image": "military_press.gif",
      "exerciseTypeKey": "1",
      "muscleGroupId": 3,
      "createdByUser": false,
      "unilateral": false
    },
    {
      "id": 32,
      "nameKey": "exercise.barbell_shoulder_press.name",
      "descriptionKey": "exercise.barbell_shoulder_press.description",
      "image": "barbell_shoulder_press.gif",
      "exerciseTypeKey": "1",
      "muscleGroupId": 3,
      "createdByUser": false,
      "unilateral": false
    },
    {
      "id": 33,
      "nameKey": "exercise.machine_shoulder_press.name",
      "descriptionKey": "exercise.machine_shoulder_press.description",
      "image": "machine_shoulder_press.gif",
      "exerciseTypeKey": "14",
      "muscleGroupId": 3,
      "createdByUser": false,
      "unilateral": false
    },
    {
      "id": 34,
      "nameKey": "exercise.rear_delt_fly.name",
      "descriptionKey": "exercise.rear_delt_fly.description",
      "image": "rear_delt_fly.gif",
      "exerciseTypeKey": "15",
      "muscleGroupId": 3,
      "createdByUser": false,
      "unilateral": false
    },
    {
      "id": 35,
      "nameKey": "exercise.rear_delt_raise.name",
      "descriptionKey": "exercise.rear_delt_raise.description",
      "image": "rear_delt_raise.gif",
      "exerciseTypeKey": "15",
      "muscleGroupId": 3,
      "createdByUser": false,
      "unilateral": false
    },
    {
      "id": 36,
      "nameKey": "exercise.dumbbell_front_raise.name",
      "descriptionKey": "exercise.dumbbell_front_raise.description",
      "image": "dumbbell_front_raise.gif",
      "exerciseTypeKey": "15",
      "muscleGroupId": 3,
      "createdByUser": false,
      "unilateral": false
    },
    {
      "id": 37,
      "nameKey": "exercise.cable_front_raise.name",
      "descriptionKey": "exercise.cable_front_raise.description",
      "image": "cable_front_raise.gif",
      "exerciseTypeKey": "13",
      "muscleGroupId": 3,
      "createdByUser": false,
      "unilateral": false
    },
    {
      "id": 38,
      "nameKey": "exercise.dumbbell_lateral_raise.name",
      "descriptionKey": "exercise.dumbbell_lateral_raise.description",
      "image": "dumbbell_lateral_raise.gif",
      "exerciseTypeKey": "15",
      "muscleGroupId": 3,
      "createdByUser": false,
      "unilateral": false
    },
    {
      "id": 39,
      "nameKey": "exercise.cable_lateral_raise.name",
      "descriptionKey": "exercise.cable_lateral_raise.description",
      "image": "cable_lateral_raise.gif",
      "exerciseTypeKey": "13",
      "muscleGroupId": 3,
      "createdByUser": false,
      "unilateral": false
    },

    {
      "id": 40,
      "nameKey": "exercise.wide_grip_pull_up.name",
      "descriptionKey": "exercise.wide_grip_pull_up.description",
      "image": "wide_grip_pull_up.gif",
      "exerciseTypeKey": "2",
      "muscleGroupId": 2,
      "createdByUser": false,
      "unilateral": false
    },
    {
      "id": 41,
      "nameKey": "exercise.close_grip_pull_up.name",
      "descriptionKey": "exercise.close_grip_pull_up.description",
      "image": "close_grip_pull_up.gif",
      "exerciseTypeKey": "2",
      "muscleGroupId": 2,
      "createdByUser": false,
      "unilateral": false
    },
    {
      "id": 42,
      "nameKey": "exercise.wide_grip_seated_row.name",
      "descriptionKey": "exercise.wide_grip_seated_row.description",
      "image": "wide_grip_seated_row.gif",
      "exerciseTypeKey": "14",
      "muscleGroupId": 2,
      "createdByUser": false,
      "unilateral": true
    },
    {
      "id": 43,
      "nameKey": "exercise.close_grip_seated_row.name",
      "descriptionKey": "exercise.close_grip_seated_row.description",
      "image": "close_grip_seated_row.gif",
      "exerciseTypeKey": "14",
      "muscleGroupId": 2,
      "createdByUser": false,
      "unilateral": false
    },
    {
      "id": 44,
      "nameKey": "exercise.wide_grip_lat_pulldown.name",
      "descriptionKey": "exercise.wide_grip_lat_pulldown.description",
      "image": "wide_grip_lat_pulldown.gif",
      "exerciseTypeKey": "14",
      "muscleGroupId": 2,
      "createdByUser": false,
      "unilateral": false
    },
    {
      "id": 45,
      "nameKey": "exercise.close_grip_lat_pulldown.name",
      "descriptionKey": "exercise.close_grip_lat_pulldown.description",
      "image": "close_grip_lat_pulldown.gif",
      "exerciseTypeKey": "14",
      "muscleGroupId": 2,
      "createdByUser": false,
      "unilateral": false
    },
    {
      "id": 46,
      "nameKey": "exercise.barbell_row.name",
      "descriptionKey": "exercise.barbell_row.description",
      "image": "barbell_row.gif",
      "exerciseTypeKey": "1",
      "muscleGroupId": 2,
      "createdByUser": false,
      "unilateral": false
    },
    {
      "id": 47,
      "nameKey": "exercise.dumbbell_shrug.name",
      "descriptionKey": "exercise.dumbbell_shrug.description",
      "image": "dumbbell_shrug.gif",
      "exerciseTypeKey": "15",
      "muscleGroupId": 2,
      "createdByUser": false,
      "unilateral": false
    },
    {
      "id": 48,
      "nameKey": "exercise.deadlift.name",
      "descriptionKey": "exercise.deadlift.description",
      "image": "deadlift.gif",
      "exerciseTypeKey": "7",
      "muscleGroupId": 2,
      "createdByUser": false,
      "unilateral": false
    },

    {
      "id": 49,
      "nameKey": "exercise.hip_abduction.name",
      "descriptionKey": "exercise.hip_abduction.description",
      "image": "hip_abduction.gif",
      "exerciseTypeKey": "14",
      "muscleGroupId": 6,
      "createdByUser": false,
      "unilateral": false
    },
    {
      "id": 50,
      "nameKey": "exercise.hip_adduction.name",
      "descriptionKey": "exercise.hip_adduction.description",
      "image": "hip_adduction.gif",
      "exerciseTypeKey": "14",
      "muscleGroupId": 6,
      "createdByUser": false,
      "unilateral": false
    },
    {
      "id": 51,
      "nameKey": "exercise.dumbbell_calf_raise.name",
      "descriptionKey": "exercise.dumbbell_calf_raise.description",
      "image": "dumbbell_calf_raise.gif",
      "exerciseTypeKey": "15",
      "muscleGroupId": 6,
      "createdByUser": false,
      "unilateral": false
    },
    {
      "id": 52,
      "nameKey": "exercise.dumbbell_lunge.name",
      "descriptionKey": "exercise.dumbbell_lunge.description",
      "image": "dumbbell_lunge.gif",
      "exerciseTypeKey": "15",
      "muscleGroupId": 6,
      "createdByUser": false,
      "unilateral": true
    },
    {
      "id": 53,
      "nameKey": "exercise.hack_squat.name",
      "descriptionKey": "exercise.hack_squat.description",
      "image": "hack_squat.gif",
      "exerciseTypeKey": "14",
      "muscleGroupId": 6,
      "createdByUser": false,
      "unilateral": false
    },
    {
      "id": 54,
      "nameKey": "exercise.seated_leg_curl.name",
      "descriptionKey": "exercise.seated_leg_curl.description",
      "image": "seated_leg_curl.gif",
      "exerciseTypeKey": "14",
      "muscleGroupId": 6,
      "createdByUser": false,
      "unilateral": false
    },
    {
      "id": 55,
      "nameKey": "exercise.lying_leg_curl.name",
      "descriptionKey": "exercise.lying_leg_curl.description",
      "image": "lying_leg_curl.gif",
      "exerciseTypeKey": "14",
      "muscleGroupId": 6,
      "createdByUser": false,
      "unilateral": false
    },
    {
      "id": 56,
      "nameKey": "exercise.leg_extension.name",
      "descriptionKey": "exercise.leg_extension.description",
      "image": "leg_extension.gif",
      "exerciseTypeKey": "14",
      "muscleGroupId": 6,
      "createdByUser": false,
      "unilateral": false
    },
    {
      "id": 57,
      "nameKey": "exercise.leg_press.name",
      "descriptionKey": "exercise.leg_press.description",
      "image": "leg_press.gif",
      "exerciseTypeKey": "14",
      "muscleGroupId": 6,
      "createdByUser": false,
      "unilateral": false
    },
    {
      "id": 58,
      "nameKey": "exercise.barbell_squat.name",
      "descriptionKey": "exercise.barbell_squat.description",
      "image": "barbell_squat.gif",
      "exerciseTypeKey": "1",
      "muscleGroupId": 6,
      "createdByUser": false,
      "unilateral": false
    },
    {
      "id": 59,
      "nameKey": "exercise.dumbbell_squat.name",
      "descriptionKey": "exercise.dumbbell_squat.description",
      "image": "dumbbell_squat.gif",
      "exerciseTypeKey": "15",
      "muscleGroupId": 6,
      "createdByUser": false,
      "unilateral": false
    },
    {
      "id": 60,
      "nameKey": "exercise.floor_crunch.name",
      "descriptionKey": "exercise.floor_crunch.description",
      "image": "floor_crunch.gif",
      "exerciseTypeKey": "2",
      "muscleGroupId": 7,
      "createdByUser": false,
      "unilateral": false
    },
    {
      "id": 61,
      "nameKey": "exercise.incline_bench_crunch.name",
      "descriptionKey": "exercise.incline_bench_crunch.description",
      "image": "incline_bench_crunch.gif",
      "exerciseTypeKey": "2",
      "muscleGroupId": 7,
      "createdByUser": false,
      "unilateral": false
    },
    {
      "id": 62,
      "nameKey": "exercise.cable_crunch.name",
      "descriptionKey": "exercise.cable_crunch.description",
      "image": "cable_crunch.gif",
      "exerciseTypeKey": "13",
      "muscleGroupId": 7,
      "createdByUser": false,
      "unilateral": false
    },
    {
      "id": 63,
      "nameKey": "exercise.oblique_crunch.name",
      "descriptionKey": "exercise.oblique_crunch.description",
      "image": "oblique_crunch.gif",
      "exerciseTypeKey": "2",
      "muscleGroupId": 7,
      "createdByUser": false,
      "unilateral": false
    }
  ]
}
